{"closers.": {"closed": [69, 32, 20, 2, 2, 1], "closers": ["Alberto Brigand\u00ec", "Lorenzo Biava", "bassimatteo", "Bas Wegh", "Pablo Orviz", "indigobot"], "id": ["158bf5cf82212e8c3cb24ddd2283e60d53c342a3", "f540c2cefa4708f1055d9c8d231bdd887645d1cc", "19ff0c443194f3899ad4eb4b5c5f9451e2d39712", "87ba4a83ce6c876d8b26453e76d684b762b4198f", "a913ab19944618785bdecfc69f06afc91cc2ef5d", "00723d090ef7af465b789f1c4fbed542c92c6cca"]}, "closers.last month": {"closed": [30, 2], "closers": ["Alberto Brigand\u00ec", "Bas Wegh"], "id": ["158bf5cf82212e8c3cb24ddd2283e60d53c342a3", "87ba4a83ce6c876d8b26453e76d684b762b4198f"]}, "closers.last year": {"closed": [69, 32, 20, 2, 2, 1], "closers": ["Alberto Brigand\u00ec", "Lorenzo Biava", "bassimatteo", "Bas Wegh", "Pablo Orviz", "indigobot"], "id": ["158bf5cf82212e8c3cb24ddd2283e60d53c342a3", "f540c2cefa4708f1055d9c8d231bdd887645d1cc", "19ff0c443194f3899ad4eb4b5c5f9451e2d39712", "87ba4a83ce6c876d8b26453e76d684b762b4198f", "a913ab19944618785bdecfc69f06afc91cc2ef5d", "00723d090ef7af465b789f1c4fbed542c92c6cca"]}, "issues.no action": {"issue_id": ["157643342", "160630916", "164496348", "165031350", "166061316", "173139945", "173140267", "174483751", "174530978", "175024064", "176578720", "182283451", "182796168", "183049709"], "summary": ["Move TOSCA nodes deployment at WF level", "Live parsing of TOSCA custom types definition file", "Update Alien4Cloud library version (now TOSCA parsing is also a separated module)", "Template full parsing and validation should happen during the synchronous phase of the WF", "Add API/AAI information in the Readme", "Exploit IAM Token exchange endpoint", "Support user's groups info during deployment", "Improve documentation", "Support differents SLAs", "Use single Configs class instead of fields injected with @Value", "Switch to Spring boot", "Fix callback info in REST DOC", "Endpoints retrieved from properties must be resilient about final baskslashes", "Support TOSCA local_storage requirement type and extended relationship definition"], "time": [356.96, 340.97, 319.01, 315.03, 308.99, 271.07, 271.07, 264.0, 263.83, 260.05, 252.07, 223.8, 221.84, 220.85], "url": ["", "", "", "", "", "", "", "", "", "", "", "", "", ""]}, "issues.no comment": {"issue_id": ["155730097", "157643342", "157863894", "158698550", "159170004", "160630916", "163371664", "164496348", "165031350", "166061316", "169334014", "173139945", "173140267", "174483751", "174530978", "175024064", "176578720", "182283451", "182796168", "183049709"], "summary": ["Change Update WF Poll task to PollUndeply command", "Move TOSCA nodes deployment at WF level", "API versioning", "Increase unit & integration tests coverage", "WF status notifications are incorrectly invoked in bulk", "Live parsing of TOSCA custom types definition file", "Use chosen cloud provider when deploying Chronos job", "Update Alien4Cloud library version (now TOSCA parsing is also a separated module)", "Template full parsing and validation should happen during the synchronous phase of the WF", "Add API/AAI information in the Readme", "[#3365] Translate a simple TOSCA Template for a cluster of services into Marathon services", "Exploit IAM Token exchange endpoint", "Support user's groups info during deployment", "Improve documentation", "Support differents SLAs", "Use single Configs class instead of fields injected with @Value", "Switch to Spring boot", "Fix callback info in REST DOC", "Endpoints retrieved from properties must be resilient about final baskslashes", "Support TOSCA local_storage requirement type and extended relationship definition"], "time": [368.88, 356.96, 356.01, 350.79, 348.83, 340.97, 325.96, 319.01, 315.03, 308.99, 292.01, 271.07, 271.07, 264.0, 263.83, 260.05, 252.07, 223.8, 221.84, 220.85], "url": ["", "", "", "", "", "", "", "", "", "", "", "", "", "", "", "", "", "", "", ""]}, "issues.no resolution": {"issue_id": ["155537925", "155730097", "157643342", "157863894", "158698550", "159170004", "160630916", "161405235", "163371664", "164496348", "165031350", "166061316", "169334014", "173139945", "173140267", "174483751", "174530978", "175024064", "176578720", "182283451", "182796168", "183049709"], "summary": ["#3095 Align security filter error response to those returned by the REST controllers", "Change Update WF Poll task to PollUndeply command", "Move TOSCA nodes deployment at WF level", "API versioning", "Increase unit & integration tests coverage", "WF status notifications are incorrectly invoked in bulk", "Live parsing of TOSCA custom types definition file", "Support resource segregation", "Use chosen cloud provider when deploying Chronos job", "Update Alien4Cloud library version (now TOSCA parsing is also a separated module)", "Template full parsing and validation should happen during the synchronous phase of the WF", "Add API/AAI information in the Readme", "[#3365] Translate a simple TOSCA Template for a cluster of services into Marathon services", "Exploit IAM Token exchange endpoint", "Support user's groups info during deployment", "Improve documentation", "Support differents SLAs", "Use single Configs class instead of fields injected with @Value", "Switch to Spring boot", "Fix callback info in REST DOC", "Endpoints retrieved from properties must be resilient about final baskslashes", "Support TOSCA local_storage requirement type and extended relationship definition"], "time": [369.75, 368.88, 356.96, 356.01, 350.79, 348.83, 340.97, 335.96, 325.96, 319.01, 315.03, 308.99, 292.01, 271.07, 271.07, 264.0, 263.83, 260.05, 252.07, 223.8, 221.84, 220.85], "url": ["", "", "", "", "", "", "", "", "", "", "", "", "", "", "", "", "", "", "", "", "", ""]}, "openers.": {"id": ["158bf5cf82212e8c3cb24ddd2283e60d53c342a3", "f540c2cefa4708f1055d9c8d231bdd887645d1cc", "19ff0c443194f3899ad4eb4b5c5f9451e2d39712", "905dc4c56f771e924e7efe87851f31ff4a44a57e", "87ba4a83ce6c876d8b26453e76d684b762b4198f", "00723d090ef7af465b789f1c4fbed542c92c6cca"], "opened": [76, 41, 16, 2, 1, 1], "openers": ["Alberto Brigand\u00ec", "Lorenzo Biava", "bassimatteo", "Alfonso", "Bas Wegh", "indigobot"]}, "openers.last month": {"id": ["158bf5cf82212e8c3cb24ddd2283e60d53c342a3", "f540c2cefa4708f1055d9c8d231bdd887645d1cc", "87ba4a83ce6c876d8b26453e76d684b762b4198f"], "opened": [25, 2, 1], "openers": ["Alberto Brigand\u00ec", "Lorenzo Biava", "Bas Wegh"]}, "openers.last year": {"id": ["158bf5cf82212e8c3cb24ddd2283e60d53c342a3", "f540c2cefa4708f1055d9c8d231bdd887645d1cc", "19ff0c443194f3899ad4eb4b5c5f9451e2d39712", "905dc4c56f771e924e7efe87851f31ff4a44a57e", "87ba4a83ce6c876d8b26453e76d684b762b4198f", "00723d090ef7af465b789f1c4fbed542c92c6cca"], "opened": [76, 41, 16, 2, 1, 1], "openers": ["Alberto Brigand\u00ec", "Lorenzo Biava", "bassimatteo", "Alfonso", "Bas Wegh", "indigobot"]}}